strike_api/__init__.py
strike_api/accounts.py
strike_api/base.py
strike_api/events.py
strike_api/invoices.py
strike_api/models/__init__.py
strike_api/models/accounts.py
strike_api/models/errors.py
strike_api/models/events.py
strike_api/models/generic.py
strike_api/models/invoices.py
strike_api/models/quotes.py
strike_api/models/rates.py
strike_api/models/subscriptions.py
strike_api/rates.py
strike_api/subscriptions.py
strike_api-0.2.1.dist-info/LICENSE
strike_api-0.2.1.dist-info/WHEEL
strike_api-0.2.1.dist-info/METADATA
strike_api-0.2.1.dist-info/RECORD
