Metadata-Version: 2.1
Name: strike-api
Version: 0.2.1
Summary: A python client for the strike api
Author: Thomas Cross
Author-email: tom.bz2@gmail.com
Requires-Python: >=3.7,<4.0
Classifier: Programming Language :: Python :: 3
Classifier: Programming Language :: Python :: 3.7
Classifier: Programming Language :: Python :: 3.8
Classifier: Programming Language :: Python :: 3.9
Classifier: Programming Language :: Python :: 3.10
Classifier: Programming Language :: Python :: 3.11
Requires-Dist: pydantic (>=1.10.2,<2.0.0)
Requires-Dist: pyhumps (>=3.8.0,<4.0.0)
Requires-Dist: requests (>=2.28.1,<3.0.0)
Project-URL: Bug Tracker, https://github.com/chmoder/strike-api/issues
Project-URL: Documentation, https://strike-api.readthedocs.io/en/latest/
Project-URL: Home Page, https://github.com/chmoder/strike-api
